project/__init__.py
project/__main__.py
101903751_topsis-1.0.0.dist-info/LICENSE
101903751_topsis-1.0.0.dist-info/METADATA
101903751_topsis-1.0.0.dist-info/WHEEL
101903751_topsis-1.0.0.dist-info/entry_points.txt
101903751_topsis-1.0.0.dist-info/top_level.txt
101903751_topsis-1.0.0.dist-info/RECORD
