Metadata-Version: 2.1
Name: 101903751-topsis
Version: 1.0.0
Summary: Assignment-4
Author: MOKSHIT GOGIA
Author-email: gogiamokshit16@gmail.com
License: MIT
Platform: UNKNOWN
Classifier: License :: OSI Approved :: MIT License
Classifier: Programming Language :: Python :: 3.6
Classifier: Programming Language :: Python :: 3.7
Classifier: Programming Language :: Python :: 3.8
License-File: LICENSE
